logchecker-4.5.12.dist-info/licenses/LICENSE
src/logChecker/__init__.py
src/logChecker/logChecker.py
logchecker-4.5.12.dist-info/METADATA
logchecker-4.5.12.dist-info/WHEEL
logchecker-4.5.12.dist-info/entry_points.txt
logchecker-4.5.12.dist-info/top_level.txt
logchecker-4.5.12.dist-info/RECORD
