Metadata-Version: 2.4
Name: logChecker
Version: 4.5.12
Summary: A simple log analysis tool
Home-page: https://github.com/laimaretto/logChecker
Author: Lucas Aimaretto
Author-email: laimaretto@gmail.com
License: BSD 3-clause
Project-URL: Templates, https://github.com/laimaretto/logTemplates
Classifier: Programming Language :: Python :: 3
Classifier: License :: OSI Approved :: BSD License
Classifier: Operating System :: OS Independent
Requires-Python: >=3.8
License-File: LICENSE
Requires-Dist: textfsm==1.1.3
Requires-Dist: pandas==2.2.2
Requires-Dist: XlsxWriter<=3.2.0,>=3.0.3
Requires-Dist: ttp<=0.9.5,>=0.9.0
Requires-Dist: numpy==1.26.4
Dynamic: author
Dynamic: author-email
Dynamic: classifier
Dynamic: description
Dynamic: description-content-type
Dynamic: home-page
Dynamic: license
Dynamic: license-file
Dynamic: project-url
Dynamic: requires-dist
Dynamic: requires-python
Dynamic: summary
